twilio_sendsms/__init__.py
twilio_sendsms/sendsms.py
twilio_sendsms-0.1.6.dist-info/METADATA
twilio_sendsms-0.1.6.dist-info/WHEEL
twilio_sendsms-0.1.6.dist-info/entry_points.txt
twilio_sendsms-0.1.6.dist-info/top_level.txt
twilio_sendsms-0.1.6.dist-info/RECORD
