Metadata-Version: 2.1
Name: twilio-sendsms
Version: 0.1.6
Summary: A utility for sending SMS using a mustache temlate
Home-page: https://github.com/omahoco/twilio-sendsms
Author: Cormac O'Mahony
Author-email: cormac@omahony.id.au
License: UNKNOWN
Platform: UNKNOWN
Classifier: Programming Language :: Python :: 3
Classifier: License :: OSI Approved :: MIT License
Classifier: Operating System :: OS Independent
Requires-Python: >=3.7
Requires-Dist: pandas
Requires-Dist: pystache
Requires-Dist: twilio
Requires-Dist: InquirerPy
